README.md
setup.cfg
setup.py
pyquicksql/__init__.py
pyquicksql/connect.py
pyquicksql.egg-info/PKG-INFO
pyquicksql.egg-info/SOURCES.txt
pyquicksql.egg-info/dependency_links.txt
pyquicksql.egg-info/requires.txt
pyquicksql.egg-info/top_level.txt
pyquicksql/logger/__init__.py
pyquicksql/logger/handler.py
pyquicksql/mysql/__init__.py
pyquicksql/mysql/mysql_lookup.py
pyquicksql/mysql/mysql_modify.py
pyquicksql/mysql/mysql_remove.py
pyquicksql/mysql/mysql_set.py
pyquicksql/utils/Database.py
pyquicksql/utils/Server.py
pyquicksql/utils/__init__.py
pyquicksql/utils/logger_enums.py
pyquicksql/utils/logger_errors.py
pyquicksql/utils/sql_enums.py
pyquicksql/utils/sql_errors.py