Metadata-Version: 2.1
Name: pyquicksql
Version: 2.2
Summary: A light-weight (out-of-the box) tool for pushing SQL (MySQL) queries, a markup-language for structured txt files and running data loggers in python.
Home-page: https://github.com/GabeCordo/python-quick-sql
Author: Gabriel Cordovado
Author-email: gabriel.cordovado@icloud.com
License: MIT
Download-URL: https://github.com/GabeCordo/python_quick_sql/archive/v_2.2.tar.gz
Keywords: MYSQL,SQLITE,LOGGING
Platform: UNKNOWN
Classifier: License :: OSI Approved :: MIT License
Classifier: Operating System :: OS Independent
